http_status_code/__init__.py
http_status_code/errors.py
http_status_code/standard.py
http_status_code-0.0.11.dist-info/LICENSE
http_status_code-0.0.11.dist-info/METADATA
http_status_code-0.0.11.dist-info/WHEEL
http_status_code-0.0.11.dist-info/top_level.txt
http_status_code-0.0.11.dist-info/RECORD
