Metadata-Version: 2.1
Name: http-status-code
Version: 0.0.11
Summary: This module contains a simple library with a single class to define HTTP status codes
Home-page: https://github.com/Quakingaspen-codehub/http_status_code
Author: Quaking Aspen
Author-email: info@quakingaspen.net
License: MIT
Platform: UNKNOWN
Classifier: Programming Language :: Python :: 3
Classifier: License :: OSI Approved :: MIT License
Classifier: Operating System :: OS Independent
Requires-Python: >=3.6
License-File: LICENSE
